<?xml version="1.0" encoding="utf-8"?>
<template xmlns:xsi="http://www.w3.org/2001/XMLSchema-instance" xmlns:xsd="http://www.w3.org/2001/XMLSchema" xmlns="http://www.kolacms.com/2013/kola">
  <components>
    <atom name="button">
      <properties>
        <property name="caption" type="text">
          <value xsi:type="fixed"><![CDATA[Beabea!]]></value>
        </property>
      </properties>
    </atom>
    <atom name="markdown">
      <properties>
        <property name="markdown" type="markdown">
          <value xsi:type="fixed"><![CDATA[#Hello there!]]></value>
        </property>
      </properties>
    </atom>
    <atom name="label">
      <properties>
        <property name="caption" type="text">
          <value xsi:type="fixed"><![CDATA[Jammies]]></value>
        </property>
      </properties>
    </atom>
  </components>
  <amendments>
    <setPropertyFixed>
      <componentPath>1</componentPath>
      <propertyName>markdown</propertyName>
      <fixedValue><![CDATA[#Hello there! Sandy!]]></fixedValue>
    </setPropertyFixed>
    <setPropertyFixed>
      <componentPath>0</componentPath>
      <propertyName>caption</propertyName>
      <fixedValue><![CDATA[Click me!]]></fixedValue>
    </setPropertyFixed>
    <setPropertyFixed>
      <componentPath>0</componentPath>
      <propertyName>caption</propertyName>
      <fixedValue><![CDATA[Click me! Please]]></fixedValue>
    </setPropertyFixed>
    <setPropertyFixed>
      <componentPath>0</componentPath>
      <propertyName>caption</propertyName>
      <fixedValue><![CDATA[Click me! Please!]]></fixedValue>
    </setPropertyFixed>
    <setPropertyFixed>
      <componentPath>1</componentPath>
      <propertyName>markdown</propertyName>
      <fixedValue><![CDATA[#Hello there!]]></fixedValue>
    </setPropertyFixed>
  </amendments>
</template>